rgevolve/matching/__init__.py
rgevolve/matching/data.h5
rgevolve/tools/__init__.py
rgevolve/tools/_version.py
rgevolve/tools/bases_available.py
rgevolve/tools/functions.py
rgevolve/tools/supersectors.py
rgevolve/tools/utils.py
rgevolve_core-0.1.1.dist-info/licenses/LICENSE
rgevolve_core-0.1.1.dist-info/METADATA
rgevolve_core-0.1.1.dist-info/WHEEL
rgevolve_core-0.1.1.dist-info/top_level.txt
rgevolve_core-0.1.1.dist-info/RECORD
