Metadata-Version: 2.4
Name: rgevolve-core
Version: 0.1.1
Summary: Package providing the core tools for Renormalization Group Evolution Matrices.
Author-email: Aleks Smolkovič <aleks.smolkovic@ijs.si>, Peter Stangl <peter.stangl@cern.ch>
License: MIT
Requires-Python: >=3.8
License-File: LICENSE
Requires-Dist: numpy
Requires-Dist: scipy
Requires-Dist: appdirs
Requires-Dist: h5py
Requires-Dist: xxhash>=2.0.0
Dynamic: license-file
